Verilog/Array-Multiplier/Bit4ArrayMultiplier.v
module bit4ArrayMultiplier(
    input [3:0] m,
    input [3:0] n,
    output [7:0] p
);

wire [2:0] c;
wire [11:0] s;

assign p[0] = m[0] & n[0];

bit4adder add1(
    .a({1'b0, (m[3:1] & {3{n[0]}})}),
    .b(m & {4{n[1]}}),
    .sum(s[3:0]),
    .cout(c[0])
);

assign p[1] = s[0];

bit4adder add2(
    .a({c[0], s[3:1]}),
    .b(m & {4{n[2]}}),
    .sum(s[7:4]),
    .cout(c[1])
);

assign p[2] = s[4];

bit4adder add3(
    .a({c[1], s[7:5]}),
    .b(m & {4{n[3]}}),
    .sum(s[11:8]),
    .cout(c[2])
);

assign p[6:3] = s[11:8];
assign p[7] = c[2];

endmodule


module bit4adder(
    input [3:0] a,
    input [3:0] b,
    output [3:0] sum,
    output cout
);

assign {cout, sum} = a + b;

endmodule

Verilog/Array-Multiplier/Bit4ArrayMultiplier_tb.v
`timescale 1ns / 1ns
`include "Bit4ArrayMultiplier.v"
module Bit4ArrayMultiplier_tb();
reg [3:0] m, n;
wire [7:0] p;
bit4ArrayMultiplier uut(
    .m(m),
    .n(n),
    .p(p)
);
initial begin
    $dumpfile("Bit4ArrayMultiplier_tb.vcd");
    $dumpvars(0, Bit4ArrayMultiplier_tb);
    m = 4'b0000; n = 4'b0000;
    #10 m = 4'b0001; n = 4'b0001;
    #10 m = 4'b0010; n = 4'b0010;
    #10 m = 4'b0011; n = 4'b0011;
    #10 m = 4'b0100; n = 4'b0100;
    #10 m = 4'b0101; n = 4'b0101;
    #10 m = 4'b0110; n = 4'b0110;
    #10 m = 4'b0111; n = 4'b0111;
    #10 m = 4'b1000; n = 4'b1000;
    #10 m = 4'b1001; n = 4'b1001;
    #10 m = 4'b1010; n = 4'b1010;
    #10 m = 4'b1011; n = 4'b1011;
    #10 m = 4'b1100; n = 4'b1100;
    #10 m = 4'b1101; n = 4'b1101;
    #10 m = 4'b1110; n = 4'b1110;
    #10 m = 4'b1111; n = 4'b1111;
    $display("Test completed");
end
endmodule

Verilog/Array-Multiplier/Bit4ArrayMultiplier_tb.vcd
$date
	Wed Sep 23 19:30:27 2026
$end
$version
	Icarus Verilog
$end
$timescale
	1ns
$end
$scope module Bit4ArrayMultiplier_tb $end
$var wire 8 ! p [7:0] $end
$var reg 4 " m [3:0] $end
$var reg 4 # n [3:0] $end
$scope module uut $end
$var wire 4 $ m [3:0] $end
$var wire 4 % n [3:0] $end
$var wire 12 & s [11:0] $end
$var wire 8 ' p [7:0] $end
$var wire 3 ( c [2:0] $end
$scope module add1 $end
$var wire 4 ) a [3:0] $end
$var wire 4 * b [3:0] $end
$var wire 4 + sum [3:0] $end
$var wire 1 , cout $end
$upscope $end
$scope module add2 $end
$var wire 4 - a [3:0] $end
$var wire 4 . b [3:0] $end
$var wire 4 / sum [3:0] $end
$var wire 1 0 cout $end
$upscope $end
$scope module add3 $end
$var wire 4 1 a [3:0] $end
$var wire 4 2 b [3:0] $end
$var wire 4 3 sum [3:0] $end
$var wire 1 4 cout $end
$upscope $end
$upscope $end
$upscope $end
$enddefinitions $end
$comment Show the parameter values. $end
$dumpall
$end
#0
$dumpvars
04
b0 3
b0 2
b0 1
00
b0 /
b0 .
b0 -
0,
b0 +
b0 *
b0 )
b0 (
b0 '
b0 &
b0 %
b0 $
b0 #
b0 "
b0 !
$end
#10
b1 !
b1 '
b1 #
b1 %
b1 "
b1 $
#20
b1 /
b1 -
b10010 &
b10 +
b10 *
b100 !
b100 '
b10 #
b10 %
b10 "
b10 $
#30
b1 3
b1 1
b10 /
b10 -
b1 )
b100100100 &
b100 +
b1001 !
b1001 '
b11 *
b11 #
b11 %
b11 "
b11 $
#40
b10 3
b0 -
b10 1
b0 +
b1001000000 &
b100 /
b100 .
b10000 !
b10000 '
b0 )
b0 *
b100 #
b100 %
b100 "
b100 $
#50
b11 3
b11 1
b1 -
b10 +
b10 )
b1101100010 &
b110 /
b11001 !
b11001 '
b101 .
b101 #
b101 %
b101 "
b101 $
#60
b100 3
b100 1
b11 -
b110 +
b110 *
b10010010110 &
b1001 /
b100100 !
b100100 '
b0 )
b110 .
b110 #
b110 %
b110 "
b110 $
#70
b101 -
b110 3
b110 1
b11 )
b1010 +
b11011001010 &
b1100 /
b110001 !
b110001 '
b111 *
b111 .
b111 #
b111 %
b111 "
b111 $
#80
b0 1
b1000 3
b0 -
b1000 2
b0 +
b100000000000 &
b0 /
b1000000 !
b1000000 '
b0 )
b0 *
b0 .
b1000 #
b1000 %
b1000 "
b1000 $
#90
b1 1
b10 /
b10 -
b100 +
b100 )
b101000100100 &
b1010 3
b1010001 !
b1010001 '
b1001 2
b1001 #
b1001 %
b1001 "
b1001 $
#100
b10 1
b101 /
b101 -
b1010 +
b1010 *
b110001011010 &
b1100 3
b1100100 !
b1100100 '
b0 )
b1010 2
b1010 #
b1010 %
b1010 "
b1010 $
#110
b100 1
b1000 /
b1000 -
b1 (
1,
b101 )
b0 +
b111110000000 &
b1111 3
b1111001 !
b1111001 '
b1011 *
b1011 2
b1011 #
b1011 %
b1011 "
b1011 $
#120
b110 1
b1100 /
00
b0 -
0,
b1100 .
b0 +
b1011000000 &
b10 3
b100 (
14
b10010000 !
b10010000 '
b0 )
b0 *
b1100 2
b1100 #
b1100 %
b1100 "
b1100 $
#130
b1000 1
b110 (
10
b11 -
b110 +
b110 )
b0 /
b10100000110 &
b101 3
b10101001 !
b10101001 '
b1101 .
b1101 2
b1101 #
b1101 %
b1101 "
b1101 $
#140
b1010 1
b111 -
b1110 +
b1110 *
b101 /
b100001011110 &
b1000 3
b11000100 !
b11000100 '
b0 )
b1110 .
b1110 2
b1110 #
b1110 %
b1110 "
b1110 $
#150
b1011 -
b111 (
1,
b1101 1
b111 )
b110 +
b1010 /
b110010100110 &
b1100 3
b11100001 !
b11100001 '
b1111 *
b1111 .
b1111 2
b1111 #
b1111 %
b1111 "
b1111 $
