Verilog/Decoder/dec3_8/dec3to8.v
module dec3to8(
    input [2:0] A,
    output [7:0] Y
);

dec2to4 dec1(
    .EN(~A[2]),
    .A(A[1:0]),
    .Y(Y[3:0])
);

dec2to4 dec2(
    .EN(A[2]),
    .A(A[1:0]),
    .Y(Y[7:4])
);

endmodule


module dec2to4(
    input EN,
    input [1:0] A,
    output reg [3:0] Y
);

always @(*) begin

    if(EN == 1'b1) begin

        case(A)
            2'b00: Y = 4'b0001;
            2'b01: Y = 4'b0010;
            2'b10: Y = 4'b0100;
            2'b11: Y = 4'b1000;
            default: Y = 4'b0000;
        endcase

    end

    else begin
        Y = 4'b0000;
    end

end

endmodule

Verilog/Decoder/dec3_8/dec3to8_tb.v
`timescale 1ns / 1ns
`include "dec3to8.v"
module dec3to8_tb();

reg [2:0]A;
wire [7:0]Y;
dec3to8 uut(
    .A(A),
    .Y(Y)
);
initial begin
    $dumpfile("dec3to8_tb.vcd");
    $dumpvars(0, dec3to8_tb);
    A = 3'b000;
    #10 A = 3'b001;
    #10 A = 3'b010;
    #10 A = 3'b011;
    #10 A = 3'b100;
    #10 A = 3'b101;
    #10 A = 3'b110;
    #10 A = 3'b111;
    $display("Test completed");
end
endmodule

Verilog/Decoder/dec3to8_tb.vcd
$date
	Sun Sep 20 11:06:26 2026
$end
$version
	Icarus Verilog
$end
$timescale
	1ns
$end
$scope module dec3to8_tb $end
$var wire 8 ! Y [7:0] $end
$var reg 3 " A [2:0] $end
$scope module uut $end
$var wire 3 # A [2:0] $end
$var wire 8 $ Y [7:0] $end
$scope module dec1 $end
$var wire 2 % A [1:0] $end
$var wire 1 & EN $end
$var reg 4 ' Y [3:0] $end
$upscope $end
$scope module dec2 $end
$var wire 2 ( A [1:0] $end
$var wire 1 ) EN $end
$var reg 4 * Y [3:0] $end
$upscope $end
$upscope $end
$upscope $end
$enddefinitions $end
$comment Show the parameter values. $end
$dumpall
$end
#0
$dumpvars
b0 *
0)
b0 (
b1 '
1&
b0 %
b1 $
b0 #
b0 "
b1 !
$end
#10
b10 !
b10 $
b10 '
b1 %
b1 (
b1 "
b1 #
#20
b100 !
b100 $
b100 '
b10 %
b10 (
b10 "
b10 #
#30
b1000 !
b1000 $
b1000 '
b11 %
b11 (
b11 "
b11 #
#40
0&
b0 '
b10000 !
b10000 $
b1 *
b0 %
1)
b0 (
b100 "
b100 #
#50
b100000 !
b100000 $
b10 *
b1 %
b1 (
b101 "
b101 #
#60
b1000000 !
b1000000 $
b100 *
b10 %
b10 (
b110 "
b110 #
#70
b10000000 !
b10000000 $
b1000 *
b11 %
b11 (
b111 "
b111 #
