Verilog/Multiplexer/8to1Mux/Mux8to1.v
module Mux8to1 (
    input [7:0] D,
    input [2:0] S,
    output wire Y
);

    wire Y1, Y2;

    Mux4to1 mux1 (
        .D(D[3:0]),
        .S(S[1:0]),
        .Y(Y1)
    );

    Mux4to1 mux2 (
        .D(D[7:4]),
        .S(S[1:0]),
        .Y(Y2)
    );

    Mux2to1 mux3 (
        .D({Y2, Y1}),
        .S(S[2]),
        .Y(Y)
    );

endmodule
module Mux4to1 (input [3:0] D, input [1:0] S, output reg Y);
    always @(*) begin
        case (S)
            2'b00: Y = D[0];
            2'b01: Y = D[1];
            2'b10: Y = D[2];
            2'b11: Y = D[3];
            default: Y = 1'b0; // Default case to avoid latches
        endcase
    end
    endmodule
    module Mux2to1 (input [1:0] D, input S, output reg Y);
    always @(*) begin
        case (S)
            1'b0: Y = D[0];
            1'b1: Y = D[1];
            default: Y = 1'b0; // Default case to avoid latches
        endcase
    end
    endmodule

Verilog/Multiplexer/8to1Mux/Mux8to1_tb.v
`timescale 1ns/1ns
`include "Mux8to1.v"
module Mux8to1_tb();

    reg [7:0] D;
    reg [2:0] S;
    wire Y;

    Mux8to1 uut (
        .D(D),
        .S(S),
        .Y(Y)
    );

    initial begin

        $dumpfile("Mux8to1_tb.vcd");
        $dumpvars(0, Mux8to1_tb);

        // Test case 1: Select D[0]
        D = 8'b10101010;
        S = 3'b000;
        #10;

        // Test case 2: Select D[1]
        D = 8'b10101010;
        S = 3'b001;
        #10;

        // Test case 3: Select D[2]
        D = 8'b10101010;
        S = 3'b010;
        #10;

        // Test case 4: Select D[3]
        D = 8'b10101010;
        S = 3'b011;
        #10;

        // Test case 5: Select D[4]
        D = 8'b10101010;
        S = 3'b100;
        #10;

        // Test case 6: Select D[5]
        D = 8'b10101010;
        S = 3'b101;
        #10;

        // Test case 7: Select D[6]
        D = 8'b10101010;
        S = 3'b110;
        #10;

        // Test case 8: Select D[7]
        D = 8'b10101010;
        S = 3'b111;
        #10;

        $display("Test completed");
        $finish;

    end
    endmodule

Verilog/Multiplexer/8to1Mux/Mux8to1_tb.vcd
$date
	Sun Sep 13 11:01:19 2026
$end
$version
	Icarus Verilog
$end
$timescale
	1ns
$end
$scope module Mux8to1_tb $end
$var wire 1 ! Y $end
$var reg 8 " D [7:0] $end
$var reg 3 # S [2:0] $end
$scope module uut $end
$var wire 8 $ D [7:0] $end
$var wire 3 % S [2:0] $end
$var wire 1 & Y2 $end
$var wire 1 ' Y1 $end
$var wire 1 ! Y $end
$scope module mux1 $end
$var wire 4 ( D [3:0] $end
$var wire 2 ) S [1:0] $end
$var reg 1 ' Y $end
$upscope $end
$scope module mux2 $end
$var wire 4 * D [3:0] $end
$var wire 2 + S [1:0] $end
$var reg 1 & Y $end
$upscope $end
$scope module mux3 $end
$var wire 2 , D [1:0] $end
$var wire 1 - S $end
$var reg 1 ! Y $end
$upscope $end
$upscope $end
$upscope $end
$enddefinitions $end
$comment Show the parameter values. $end
$dumpall
$end
#0
$dumpvars
0-
b0 ,
b0 +
b1010 *
b0 )
b1010 (
0'
0&
b0 %
b10101010 $
b0 #
b10101010 "
0!
$end
#10
1!
1'
b11 ,
1&
b1 )
b1 +
b1 #
b1 %
#20
0!
0'
b0 ,
0&
b10 )
b10 +
b10 #
b10 %
#30
1!
1'
b11 ,
1&
b11 )
b11 +
b11 #
b11 %
#40
0!
0'
b0 ,
0&
b0 )
b0 +
1-
b100 #
b100 %
#50
1!
1'
b11 ,
1&
b1 )
b1 +
b101 #
b101 %
#60
0!
0'
b0 ,
0&
b10 )
b10 +
b110 #
b110 %
#70
1!
1'
b11 ,
1&
b11 )
b11 +
b111 #
b111 %
