Verilog/BasicGates/Solution1.v
module Solution1(input [3:0] x, output f);
wire a,b,c,d,g,h;

and(a,x[0],x[2]);
and(b,x[1],x[3]);
or(g,a,b);

or(c,x[0],~x[2]);
or(d,~x[1],x[3]);
and(h,c,d);

or(f,g,h);

endmodule

Verilog/BasicGates/Solution1_tb.v
`timescale 1ns / 1ns
`include "Solution1.v"
module Solution1_tb();
reg [3:0]x;
wire f;
Solution1 uut(
    .x(x),
    .f(f)
);
initial begin
    $dumpfile("Solution1_tb.vcd");
    $dumpvars(0, Solution1_tb);
    x = 4'b0000;
    #10 x = 4'b0001;
    #10 x = 4'b0010;
    #10 x = 4'b0011;
    #10 x = 4'b0100;
    #10 x = 4'b0101;
    #10 x = 4'b0110;
    #10 x = 4'b0111;
    #10 x = 4'b1000;
    #10 x = 4'b1001;
    #10 x = 4'b1010;
    #10 x = 4'b1011;
    #10 x = 4'b1100;
    #10 x = 4'b1101;
    #10 x = 4'b1110;
    #10 x = 4'b1111;
    $display("Test completed");
end
endmodule

Verilog/BasicGates/Solution1_tb.vcd
$date
	Wed Sep 23 18:18:09 2026
$end
$version
	Icarus Verilog
$end
$timescale
	1ns
$end
$scope module Solution1_tb $end
$var wire 1 ! f $end
$var reg 4 " x [3:0] $end
$scope module uut $end
$var wire 1 # a $end
$var wire 1 $ b $end
$var wire 1 % c $end
$var wire 1 & d $end
$var wire 1 ! f $end
$var wire 1 ' g $end
$var wire 1 ( h $end
$var wire 4 ) x [3:0] $end
$upscope $end
$upscope $end
$enddefinitions $end
$comment Show the parameter values. $end
$dumpall
$end
#0
$dumpvars
b0 )
1(
0'
1&
1%
0$
0#
b0 "
1!
$end
#10
b1 "
b1 )
#20
0!
0(
0&
b10 "
b10 )
#30
b11 "
b11 )
#40
1&
0%
b100 "
b100 )
#50
1!
1'
1(
1#
1%
b101 "
b101 )
#60
0!
0'
0(
0&
0#
0%
b110 "
b110 )
#70
1!
1'
1#
1%
b111 "
b111 )
#80
0'
1(
0#
1&
b1000 "
b1000 )
#90
b1001 "
b1001 )
#100
1'
1$
b1010 "
b1010 )
#110
b1011 "
b1011 )
#120
0!
0'
0(
0$
0%
b1100 "
b1100 )
#130
1!
1'
1(
1#
1%
b1101 "
b1101 )
#140
0(
0#
1$
0%
b1110 "
b1110 )
#150
1(
1#
1%
b1111 "
b1111 )
