Verilog/Counters/JohnsonCounter/JCounter.v
module JCounter (
    input clk,reset,
    output wire [3:0] q
);
dff dff0(.clk(clk), .reset(reset), .d(~q[3]), .q(q[0]));
dff dff1(.clk(clk), .reset(reset), .d(q[0]), .q(q[1]));
dff dff2(.clk(clk), .reset(reset), .d(q[1]), .q(q[2]));
dff dff3(.clk(clk), .reset(reset), .d(q[2]), .q(q[3]));
endmodule
module dff(
    input clk,
    input reset,
    input d,
    output reg q
);

    always @(posedge clk) begin
        if (reset)
            q <= 1'b0;
        else
            q <= d;
    end

endmodule

Verilog/Counters/JohnsonCounter/JCounter_tb.v
`timescale 1ns / 1ns
`include "JCounter.v"

module JCounter_tb();

reg clk, reset;
wire [3:0] q;

JCounter uut(
    .clk(clk),
    .reset(reset),
    .q(q)
);

initial begin
    $dumpfile("JCounter_tb.vcd");
    $dumpvars(0, JCounter_tb);

    clk = 0;
    reset = 1;

    #10 reset = 0;

    #100 $finish;
end

always #5 clk = ~clk;

endmodule

Verilog/Counters/JohnsonCounter/JCounter_tb.vcd
$date
	Mon Sep 28 21:39:43 2026
$end
$version
	Icarus Verilog
$end
$timescale
	1ns
$end
$scope module JCounter_tb $end
$var wire 4 ! q [3:0] $end
$var reg 1 " clk $end
$var reg 1 # reset $end
$scope module uut $end
$var wire 1 " clk $end
$var wire 1 # reset $end
$var wire 4 $ q [3:0] $end
$scope module dff0 $end
$var wire 1 " clk $end
$var wire 1 % d $end
$var wire 1 # reset $end
$var reg 1 & q $end
$upscope $end
$scope module dff1 $end
$var wire 1 " clk $end
$var wire 1 ' d $end
$var wire 1 # reset $end
$var reg 1 ( q $end
$upscope $end
$scope module dff2 $end
$var wire 1 " clk $end
$var wire 1 ) d $end
$var wire 1 # reset $end
$var reg 1 * q $end
$upscope $end
$scope module dff3 $end
$var wire 1 " clk $end
$var wire 1 + d $end
$var wire 1 # reset $end
$var reg 1 , q $end
$upscope $end
$upscope $end
$upscope $end
$enddefinitions $end
$comment Show the parameter values. $end
$dumpall
$end
#0
$dumpvars
x,
x+
x*
x)
x(
x'
x&
x%
bx $
1#
0"
bx !
$end
#5
1%
0'
0)
0+
0&
0(
0*
b0 !
b0 $
0,
1"
#10
0"
0#
#15
1'
b1 !
b1 $
1&
1"
#20
0"
#25
1)
b11 !
b11 $
1(
1"
#30
0"
#35
1+
b111 !
b111 $
1*
1"
#40
0"
#45
0%
b1111 !
b1111 $
1,
1"
#50
0"
#55
0'
b1110 !
b1110 $
0&
1"
#60
0"
#65
0)
b1100 !
b1100 $
0(
1"
#70
0"
#75
0+
b1000 !
b1000 $
0*
1"
#80
0"
#85
1%
b0 !
b0 $
0,
1"
#90
0"
#95
1'
b1 !
b1 $
1&
1"
#100
0"
#105
1)
b11 !
b11 $
1(
1"
